materialxMaterials/GPUOpenLoader.py
materialxMaterials/GPUOpenLoaderCmd.py
materialxMaterials/__init__.py
materialxMaterials/__main__.py
materialxMaterials/ambientCGLoader.py
materialxMaterials/ambientCGLoaderCmd.py
materialxMaterials/physicallyBasedMaterialX.py
materialxMaterials/physicallyBasedMaterialXCmd.py
materialxMaterials/polyHavenLoader.py
materialxMaterials/polyHavenLoaderCmd.py
materialxMaterials-1.39.4.dist-info/LICENSE
materialxMaterials-1.39.4.dist-info/METADATA
materialxMaterials-1.39.4.dist-info/WHEEL
materialxMaterials-1.39.4.dist-info/entry_points.txt
materialxMaterials-1.39.4.dist-info/top_level.txt
materialxMaterials-1.39.4.dist-info/RECORD
