Metadata-Version: 2.1
Name: materialxMaterials
Version: 1.39.4
Summary: Utilities to get materials stored on a remote server
Author-email: Bernard Kwok <kwokcb@gmail.com>
License: Apache License
Project-URL: Homepage, https://kwokcb.github.io/materialxMaterials/
Project-URL: Issues, https://github.com/kwokcb/materialxMaterials/issues
Project-URL: Source Code, https://github.com/kwokcb/materialxMaterials
Project-URL: Documentation, https://kwokcb.github.io/materialxMaterials/
Classifier: Intended Audience :: Developers
Classifier: Programming Language :: Python :: 3
Classifier: License :: OSI Approved :: MIT License
Classifier: Operating System :: OS Independent
Classifier: Topic :: Software Development :: Libraries :: Python Modules
Requires-Python: >=3.8
License-File: LICENSE
Requires-Dist: materialx==1.39.4
Requires-Dist: requests
Requires-Dist: pillow
